Metadata-Version: 2.1
Name: self-attention-cv
Version: 1.2.3
Summary: Self-attention building blocks for computer vision applications in PyTorch
Home-page: https://github.com/The-AI-Summer/self_attention_cv
Author: Adaloglou Nikolas
Author-email: nikolas@theaiusummer.com
License: MIT
Platform: UNKNOWN
Classifier: License :: OSI Approved :: MIT License
Classifier: Programming Language :: Python :: 3
Classifier: Programming Language :: Python :: 3.7
Requires-Python: >=3.6
License-File: LICENSE
Requires-Dist: torch (>=1.7)
Requires-Dist: torchvision (>=0.8)
Requires-Dist: einops (>=0.3)
Requires-Dist: numpy (>=1.19)
Requires-Dist: pytest (>=6.2)
